fast_speedtest/__init__.py
fast_speedtest/_version.py
fast_speedtest/api.py
fast_speedtest/cli.py
fast_speedtest/utils.py
fastcom_speed_cli-0.1.6.dist-info/LICENSE
fastcom_speed_cli-0.1.6.dist-info/METADATA
fastcom_speed_cli-0.1.6.dist-info/WHEEL
fastcom_speed_cli-0.1.6.dist-info/entry_points.txt
fastcom_speed_cli-0.1.6.dist-info/top_level.txt
fastcom_speed_cli-0.1.6.dist-info/RECORD
