Metadata-Version: 2.1
Name: fastcom-speed-cli
Version: 0.1.6
Summary: This package provides a command-line and Python interface for netflix's fast.com for speedtest
Author: Ling Wang
License: MIT License
Project-URL: repository, https://github.com/braindevices/python-fast-cli
Requires-Python: >=3.10
License-File: LICENSE
Requires-Dist: playwright>=1.45.1
